[{"hour":0,"count":2413},{"hour":1,"count":570},{"hour":2,"count":612},{"hour":3,"count":517},{"hour":4,"count":445},{"hour":5,"count":338},{"hour":6,"count":453},{"hour":7,"count":740},{"hour":8,"count":718},{"hour":9,"count":1706},{"hour":10,"count":1301},{"hour":11,"count":1268},{"hour":12,"count":1649},{"hour":13,"count":1325},{"hour":14,"count":1578},{"hour":15,"count":2380},{"hour":16,"count":1382},{"hour":17,"count":1244},{"hour":18,"count":1056},{"hour":19,"count":1056},{"hour":20,"count":2844},{"hour":21,"count":1350},{"hour":22,"count":1259},{"hour":23,"count":1215}]